toolkits-0.2.10.dist-info/METADATA
toolkits-0.2.10.dist-info/WHEEL
toolkits-0.2.10.dist-info/entry_points.txt
toolkits/3des/3des.py
toolkits/3des/__init__.py
toolkits/__init__.py
toolkits/basic/__init__.py
toolkits/basic/list_helper.py
toolkits/config_parser/__init__.py
toolkits/config_parser/config_demo.py
toolkits/config_parser/config_groups_helper.py
toolkits/config_parser/config_helper.py
toolkits/config_parser/env_prepare.py
toolkits/databases/__init__.py
toolkits/databases/database_client_util.py
toolkits/databases/es_client.py
toolkits/databases/hive_client.py
toolkits/databases/hive_cmd.py
toolkits/databases/hive_helper.py
toolkits/databases/mysql_helper.py
toolkits/databases/redis_mgmt.py
toolkits/databases/sql_helper.py
toolkits/databases/sqlalchemy_helper.py
toolkits/databases/status_check.py
toolkits/db_query_demo.py
toolkits/libs_core/__init__.py
toolkits/libs_core/load_module.py
toolkits/network/__init__.py
toolkits/network/ip_helper.py
toolkits/network/pdi_helper.py
toolkits/network/send_mail.py
toolkits/system/__init__.py
toolkits/system/aes_cipher.py
toolkits/system/basic_utils.py
toolkits/system/collections_helper.py
toolkits/system/crpyt_helper.py
toolkits/system/dict2xml.py
toolkits/system/dict_helper.py
toolkits/system/excel_helper.py
toolkits/system/file_helper.py
toolkits/system/load_module.py
toolkits/system/priority_tasks.py
toolkits/system/process_monitor/__init__.py
toolkits/system/process_monitor/process_monitor.py
toolkits/system/shell_helper.py
toolkits/system/str_helper.py
toolkits/system/tasks_deamon/__init__.py
toolkits/system/tasks_deamon/tasks_controller.py
toolkits/system/tasks_deamon/tasks_multiprocessing.py
toolkits/system/tasks_deamon/tasks_process.py
toolkits/system/test_shell_helper.py
toolkits/system/time_helper.py
toolkits/system/win32_env.py
toolkits/tookits_app.py
toolkits/tookits_cli.py
toolkits-0.2.10.dist-info/RECORD
