Metadata-Version: 2.1
Name: toolkits
Version: 0.2.10
Summary: toolkits for quickly reference
Author-Email: li_jia_yue <59727816@qq.com>
License: MIT
Requires-Python: >=3.9
Requires-Dist: fire>=0.6.0
Requires-Dist: arrow>=1.3.0
Requires-Dist: pytest>=8.2.2
Requires-Dist: icecream>=2.1.3
Requires-Dist: schedule>=1.2.2
Requires-Dist: jmespath>=1.0.1
Requires-Dist: unicodecsv>=0.14.1
Requires-Dist: log4python>=1.0.11
Requires-Dist: unipath>=1.1
